ug4py_base-0.2.3.dist-info/RECORD
ug4py_base-0.2.3.dist-info/WHEEL
ug4py_base-0.2.3.dist-info/METADATA
ug4py_base-0.2.3.dist-info/licenses/LICENSE
ug4py/pylimex.cpython-310-darwin.so
ug4py/pyconvectiondiffusion.cpython-310-darwin.so
ug4py/pyutil.cpython-310-darwin.so
ug4py/pyugcore.cpython-310-darwin.so
lib/libug4_s.a
