Metadata-Version: 2.2
Name: ug4py-base
Version: 0.2.3
Summary: This is a basic python package for UG4.
